{
  "item": {
    "id": "N0393",
    "source_root": "E:\\BaiduNetdiskDownload\\26年6月新增：薛辉价值30000 线下达人班",
    "relative_path": "赠1：25年新版学员高清手册（带小黄本）\\055.jpg",
    "name": "055.jpg",
    "extension": ".jpg",
    "media_type": "image",
    "size_bytes": 912183,
    "initial_category": "个人IP",
    "full_path": "E:\\BaiduNetdiskDownload\\26年6月新增：薛辉价值30000 线下达人班\\赠1：25年新版学员高清手册（带小黄本）\\055.jpg"
  },
  "lines": [
    "Allin",
    "讲故事脚本模版训练",
    "短视频达人训练中",
    "脚本类型",
    "脚本类型",
    "所属桥段",
    "内容",
    "第一轮",
    "FIBST BUUNO",
    "国境",
    "手资料禁止传播闲鱼I1D有神灯的阿拉了",
    "第一轮",
    "FIRST HDUND",
    "转机",
    "第二轮",
    "SECONO BOUNO",
    "国境",
    "第二轮",
    "SEEOND ROUNO",
    "转美型",
    "转机",
    "感悟",
    "51"
  ],
  "raw": [
    {
      "text": "Allin",
      "score": 0.9770673513412476,
      "box": [
        [
          1881.5,
          286.1129150390625
        ],
        [
          2107.63330078125,
          286.1129150390625
        ],
        [
          2107.63330078125,
          372.6532287597656
        ],
        [
          1881.5,
          372.6532287597656
        ]
      ]
    },
    {
      "text": "讲故事脚本模版训练",
      "score": 0.9897908965746561,
      "box": [
        [
          681.933349609375,
          312.6048278808594
        ],
        [
          1734.86669921875,
          316.1370849609375
        ],
        [
          1734.86669921875,
          415.0403137207031
        ],
        [
          681.933349609375,
          411.508056640625
        ]
      ]
    },
    {
      "text": "短视频达人训练中",
      "score": 0.9957616329193115,
      "box": [
        [
          1877.9666748046875,
          385.01611328125
        ],
        [
          2270.166748046875,
          385.01611328125
        ],
        [
          2270.166748046875,
          425.6370849609375
        ],
        [
          1877.9666748046875,
          425.6370849609375
        ]
      ]
    },
    {
      "text": "脚本类型",
      "score": 0.9976982474327087,
      "box": [
        [
          166.06666564941406,
          619.9112548828125
        ],
        [
          425.76666259765625,
          623.4435424804688
        ],
        [
          425.76666259765625,
          697.6209716796875
        ],
        [
          166.06666564941406,
          694.0886840820312
        ]
      ]
    },
    {
      "text": "脚本类型",
      "score": 0.971423476934433,
      "box": [
        [
          1273.7666015625,
          623.4435424804688
        ],
        [
          1468.0999755859375,
          623.4435424804688
        ],
        [
          1468.0999755859375,
          683.491943359375
        ],
        [
          1273.7666015625,
          683.491943359375
        ]
      ]
    },
    {
      "text": "所属桥段",
      "score": 0.9979192465543747,
      "box": [
        [
          438.1333312988281,
          928.98388671875
        ],
        [
          795.0,
          928.98388671875
        ],
        [
          795.0,
          1001.3951416015625
        ],
        [
          438.1333312988281,
          1001.3951416015625
        ]
      ]
    },
    {
      "text": "内容",
      "score": 0.9983230531215668,
      "box": [
        [
          1869.13330078125,
          928.98388671875
        ],
        [
          2044.0333251953125,
          928.98388671875
        ],
        [
          2044.0333251953125,
          1010.2257690429688
        ],
        [
          1869.13330078125,
          1010.2257690429688
        ]
      ]
    },
    {
      "text": "第一轮",
      "score": 0.9961017568906149,
      "box": [
        [
          210.23333740234375,
          1192.1370849609375
        ],
        [
          374.5333251953125,
          1192.1370849609375
        ],
        [
          374.5333251953125,
          1248.6531982421875
        ],
        [
          210.23333740234375,
          1248.6531982421875
        ]
      ]
    },
    {
      "text": "FIBST BUUNO",
      "score": 0.6733438724821265,
      "box": [
        [
          210.23333740234375,
          1245.1209716796875
        ],
        [
          372.76666259765625,
          1245.1209716796875
        ],
        [
          372.76666259765625,
          1269.8468017578125
        ],
        [
          210.23333740234375,
          1269.8468017578125
        ]
      ]
    },
    {
      "text": "国境",
      "score": 0.9065928161144257,
      "box": [
        [
          201.39999389648438,
          1289.274169921875
        ],
        [
          386.8999938964844,
          1289.274169921875
        ],
        [
          386.8999938964844,
          1384.6451416015625
        ],
        [
          201.39999389648438,
          1384.6451416015625
        ]
      ]
    },
    {
      "text": "手资料禁止传播闲鱼I1D有神灯的阿拉了",
      "score": 0.8994006545920121,
      "box": [
        [
          280.8999938964844,
          1305.1693115234375
        ],
        [
          1581.1666259765625,
          2280.072509765625
        ],
        [
          1501.6666259765625,
          2384.274169921875
        ],
        [
          203.1666717529297,
          1409.3709716796875
        ]
      ]
    },
    {
      "text": "第一轮",
      "score": 0.9950760205586752,
      "box": [
        [
          210.23333740234375,
          1649.564453125
        ],
        [
          378.066650390625,
          1653.0968017578125
        ],
        [
          376.29998779296875,
          1714.9112548828125
        ],
        [
          208.46665954589844,
          1711.3790283203125
        ]
      ]
    },
    {
      "text": "FIRST HDUND",
      "score": 0.7112072028897025,
      "box": [
        [
          210.23333740234375,
          1704.314453125
        ],
        [
          376.29998779296875,
          1707.8468017578125
        ],
        [
          376.29998779296875,
          1737.8709716796875
        ],
        [
          210.23333740234375,
          1734.3387451171875
        ]
      ]
    },
    {
      "text": "转机",
      "score": 0.9996514022350311,
      "box": [
        [
          194.3333282470703,
          1748.4677734375
        ],
        [
          386.8999938964844,
          1748.4677734375
        ],
        [
          386.8999938964844,
          1843.8387451171875
        ],
        [
          194.3333282470703,
          1843.8387451171875
        ]
      ]
    },
    {
      "text": "第二轮",
      "score": 0.9997260173161825,
      "box": [
        [
          208.46665954589844,
          2112.290283203125
        ],
        [
          376.29998779296875,
          2115.822509765625
        ],
        [
          374.5333251953125,
          2177.636962890625
        ],
        [
          206.6999969482422,
          2174.104736328125
        ]
      ]
    },
    {
      "text": "SECONO BOUNO",
      "score": 0.854580283164978,
      "box": [
        [
          210.23333740234375,
          2168.806396484375
        ],
        [
          374.5333251953125,
          2168.806396484375
        ],
        [
          374.5333251953125,
          2198.83056640625
        ],
        [
          210.23333740234375,
          2198.83056640625
        ]
      ]
    },
    {
      "text": "国境",
      "score": 0.8822151124477386,
      "box": [
        [
          201.39999389648438,
          2211.193603515625
        ],
        [
          388.6666564941406,
          2211.193603515625
        ],
        [
          388.6666564941406,
          2306.564453125
        ],
        [
          201.39999389648438,
          2306.564453125
        ]
      ]
    },
    {
      "text": "第二轮",
      "score": 0.9992581804593405,
      "box": [
        [
          212.0,
          2575.01611328125
        ],
        [
          378.066650390625,
          2578.54833984375
        ],
        [
          376.29998779296875,
          2640.36279296875
        ],
        [
          210.23333740234375,
          2636.83056640625
        ]
      ]
    },
    {
      "text": "SEEOND ROUNO",
      "score": 0.7633926123380661,
      "box": [
        [
          210.23333740234375,
          2633.29833984375
        ],
        [
          376.29998779296875,
          2633.29833984375
        ],
        [
          376.29998779296875,
          2663.322509765625
        ],
        [
          210.23333740234375,
          2663.322509765625
        ]
      ]
    },
    {
      "text": "转美型",
      "score": 0.7247029741605123,
      "box": [
        [
          717.2666625976562,
          2636.83056640625
        ],
        [
          934.566650390625,
          2636.83056640625
        ],
        [
          934.566650390625,
          2691.58056640625
        ],
        [
          717.2666625976562,
          2691.58056640625
        ]
      ]
    },
    {
      "text": "转机",
      "score": 0.9991571605205536,
      "box": [
        [
          194.3333282470703,
          2675.685546875
        ],
        [
          383.3666687011719,
          2675.685546875
        ],
        [
          383.3666687011719,
          2771.056396484375
        ],
        [
          194.3333282470703,
          2771.056396484375
        ]
      ]
    },
    {
      "text": "感悟",
      "score": 0.9964069426059723,
      "box": [
        [
          220.8333282470703,
          3094.258056640625
        ],
        [
          362.1666564941406,
          3090.725830078125
        ],
        [
          363.9333190917969,
          3159.604736328125
        ],
        [
          222.59999084472656,
          3163.136962890625
        ]
      ]
    },
    {
      "text": "51",
      "score": 0.9966386258602142,
      "box": [
        [
          1166.0,
          3309.725830078125
        ],
        [
          1233.13330078125,
          3309.725830078125
        ],
        [
          1233.13330078125,
          3368.008056640625
        ],
        [
          1166.0,
          3368.008056640625
        ]
      ]
    }
  ]
}