{
  "item": {
    "id": "N0422",
    "source_root": "E:\\BaiduNetdiskDownload\\26年6月新增：薛辉价值30000 线下达人班",
    "relative_path": "赠1：25年新版学员高清手册（带小黄本）\\脚本+转盘\\015.jpg",
    "name": "015.jpg",
    "extension": ".jpg",
    "media_type": "image",
    "size_bytes": 2261460,
    "initial_category": "个人IP",
    "full_path": "E:\\BaiduNetdiskDownload\\26年6月新增：薛辉价值30000 线下达人班\\赠1：25年新版学员高清手册（带小黄本）\\脚本+转盘\\015.jpg"
  },
  "lines": [
    "事件结束",
    "一手资料禁止传播闲鱼ID有袖",
    "打的阿拉"
  ],
  "raw": [
    {
      "text": "事件结束",
      "score": 0.9676584750413895,
      "box": [
        [
          340.9666748046875,
          1356.3870849609375
        ],
        [
          466.3999938964844,
          1358.1531982421875
        ],
        [
          457.566650390625,
          1861.5
        ],
        [
          332.1333312988281,
          1859.73388671875
        ]
      ]
    },
    {
      "text": "一手资料禁止传播闲鱼ID有袖",
      "score": 0.9465573728084564,
      "box": [
        [
          450.5,
          1748.4677734375
        ],
        [
          1605.9000244140625,
          2198.83056640625
        ],
        [
          1558.199951171875,
          2320.693603515625
        ],
        [
          402.79998779296875,
          1870.3306884765625
        ]
      ]
    },
    {
      "text": "打的阿拉",
      "score": 0.633788026869297,
      "box": [
        [
          1607.6666259765625,
          2235.91943359375
        ],
        [
          2010.4666748046875,
          2394.870849609375
        ],
        [
          1980.433349609375,
          2472.58056640625
        ],
        [
          1577.63330078125,
          2313.62890625
        ]
      ]
    }
  ]
}